{
  "symbol": "BTCUSDT",
  "time": "2022-09-16 16:25:45.090758",
  "label_return": 0.0033200353423117083,
  "indicators": {
    "SMA": 18764.82,
    "EMA": 18782.68569551062,
    "Trend15": "Down",
    "RSI": 69.60167714884696,
    "MACD": {
      "MACDLine": -2.078302637422894,
      "SignalLine": -54.12294460848797,
      "Histogram": 52.044641971065076
    },
    "ATR": 82.39285714285714,
    "ATRPercent": 0.4396161409820571,
    "ADX": 6.201258280495418,
    "Volume": "Volume Down",
    "Supports": [
      19435,
      19627.5,
      19455,
      19315,
      19369,
      19551.5,
      19677.5,
      19682,
      19862,
      19813,
      19820,
      19770.5,
      19811,
      19790.5,
      19851,
      19852,
      19805,
      19823.5,
      19734,
      19838,
      19862,
      19922,
      20019,
      20032.5,
      20009.5,
      19966,
      19973,
      19917.5,
      20083.5,
      19949,
      19964.5,
      19971,
      19971,
      19938,
      19989.5,
      20030,
      20022.5,
      20014,
      19749,
      19881,
      19871.5,
      19850,
      19929.5,
      19716.5,
      19625,
      19627,
      19657.5,
      19600,
      19550,
      19591.5,
      19380.5,
      19333,
      19350,
      19374.5,
      19428,
      19388,
      18630,
      18687.5,
      18296,
      18110,
      18415,
      18358,
      18610
    ],
    "Resistances": [
      19793.5,
      19586.5,
      19483,
      19622.5,
      19640,
      19678.5,
      19815.5,
      19763.5,
      20079.5,
      20044,
      20043.5,
      19976,
      19864.5,
      19848,
      19880,
      19881,
      19907,
      19885,
      19859.5,
      19857,
      19866.5,
      19946,
      20025,
      20176.5,
      20166,
      20087.5,
      20086.5,
      20079.5,
      20084,
      20117,
      20135,
      20132,
      20043.5,
      20038.5,
      20081.5,
      20073.5,
      20092,
      20065,
      20033.5,
      19939,
      20015,
      20000,
      19866,
      19869.5,
      19755,
      19739.5,
      19699.5,
      19739.5,
      19745,
      19532,
      19521,
      19509.5,
      19469,
      18820,
      18811,
      18859.5,
      18823.5,
      18818.5,
      18498.5,
      18480,
      18524.5,
      18426.5,
      18793.5
    ],
    "Patterns": {
      "bearish_engulfing": false,
      "black_solders": false,
      "builish_engulfing": false,
      "doji": false,
      "dragonfly_doji": false,
      "gravestone_doji": false,
      "hammer": false,
      "white_solders": true
    }
  }
}