{
  "symbol": "BTCUSDT",
  "time": "2026-04-23 02:25:03.541202",
  "label_return": -0.0017653301449003745,
  "indicators": {
    "SMA": 77818.22400000002,
    "EMA": 77859.58450518381,
    "Trend15": "Flat",
    "RSI": 33.51943311144555,
    "MACD": {
      "MACDLine": 4.066824875349994,
      "SignalLine": 33.32558853416898,
      "Histogram": -29.258763658818985
    },
    "ATR": 78.82857142857081,
    "ATRPercent": 0.10125907716609565,
    "ADX": 8.325520384042937,
    "Volume": "Volume Down",
    "Supports": [
      78049.1,
      77975.9,
      78035.7,
      78059.9,
      78146.2,
      78141.8,
      78162.2,
      78197.7,
      78221.1,
      78220.9,
      78187,
      78169,
      78111.5,
      78112.1,
      77994.5,
      77992.7,
      77940.7,
      77930.9,
      77814.3,
      77944.4,
      77961,
      77973.1,
      77928.8,
      77933.7,
      77791.5,
      77831.5,
      77789.4,
      77780.9,
      77805,
      77874.5,
      77914.3,
      77793.1,
      77788.1,
      77677,
      77670.6,
      77670.2,
      77632.8,
      77806.2,
      77603.6,
      77663.4,
      77555.2,
      77616.9,
      77587,
      77787,
      77769,
      77748,
      77768.3,
      77620.5,
      77648.9,
      77576.6,
      77539.2,
      77748.2,
      77910.5,
      77957.1,
      77971.2,
      77917.7,
      77897,
      77822
    ],
    "Resistances": [
      78113.2,
      78181.6,
      78200,
      78242,
      78286.4,
      78297,
      78243,
      78219.1,
      78243,
      78220.1,
      78190.5,
      78220.8,
      78173,
      78233,
      78188.5,
      78117.5,
      78150,
      78001,
      77977.5,
      77975.7,
      78000.9,
      77993.7,
      78041.8,
      77988.1,
      78004.7,
      77946.3,
      77826.6,
      77859.3,
      77843.7,
      77838,
      77839.2,
      77870.8,
      77922,
      77988.3,
      78018,
      77976.6,
      77831.3,
      77858.4,
      77729.7,
      77738.8,
      77766.1,
      77800,
      77886.6,
      77840,
      77790.6,
      77770,
      77750,
      77660,
      77669,
      77685.2,
      77729.7,
      77854,
      77833.2,
      77837.7,
      77819.9,
      77850,
      77852.2,
      77707.3,
      77692,
      77730.3,
      77669,
      77754.3,
      77869.8,
      77992.9,
      78058.5,
      78046.5,
      78075,
      78009.4,
      78005.7,
      77894.1
    ],
    "Patterns": {
      "bearish_engulfing": false,
      "black_solders": false,
      "builish_engulfing": false,
      "doji": false,
      "dragonfly_doji": false,
      "gravestone_doji": false,
      "hammer": false,
      "white_solders": false
    }
  }
}