{
  "symbol": "BTCUSDT",
  "time": "2026-03-29 02:25:03.541202",
  "label_return": 0.00496216930179807,
  "indicators": {
    "SMA": 66398.698,
    "EMA": 66397.80669053108,
    "Trend15": "Flat",
    "RSI": 29.67157417893027,
    "MACD": {
      "MACDLine": -9.949312663506134,
      "SignalLine": -6.397514082155087,
      "Histogram": -3.551798581351047
    },
    "ATR": 34.19999999999813,
    "ATRPercent": 0.051527752666784374,
    "ADX": 28.845757419698387,
    "Volume": "Volume Down",
    "Supports": [
      65993,
      66042.9,
      65975,
      65938.3,
      65924.2,
      65957.1,
      65790,
      64935.7,
      65000,
      66159,
      66300.2,
      66317,
      66320.7,
      66326.9,
      66273.2,
      66236.6,
      66184,
      66206.1,
      66622.7,
      66646.8,
      66571.5,
      66601.5,
      66619.2,
      66603.5,
      66617.4,
      66470,
      66510.9,
      66556.6,
      66570.1,
      66543.4,
      66529.7,
      66529.3,
      66606.6,
      66660.1,
      66643.5,
      66675,
      66598.3,
      66514.7,
      66450,
      66410.6,
      66287.5,
      66307.3,
      66353.6,
      66352.8,
      66304.4,
      66342.4,
      66364.2,
      66369.2,
      66387.2,
      66380,
      66377.9,
      66350.1,
      66366.7,
      66388.7,
      66401,
      66388.7,
      66367.1,
      66362,
      66361.5
    ],
    "Resistances": [
      66273.5,
      66233,
      66221.1,
      66106.7,
      66054.2,
      66126,
      66377.9,
      65930.7,
      65933.2,
      66246.8,
      66243.8,
      66412.8,
      66377.8,
      66388.4,
      66392.8,
      66475,
      66290.4,
      66428,
      66733,
      66680.3,
      66673.7,
      66626.5,
      66674.1,
      66650,
      66526.1,
      66539.9,
      66644.3,
      66561.7,
      66594,
      66568.8,
      66634.9,
      66673.4,
      66688,
      66690.4,
      66732.7,
      66765.9,
      66689,
      66568.8,
      66494.7,
      66348.7,
      66394.8,
      66398.9,
      66367.5,
      66454.8,
      66432.3,
      66408.1,
      66442.6,
      66407.2,
      66417.8,
      66419.9,
      66430,
      66437.1,
      66429.7,
      66514.2,
      66439.7,
      66398,
      66386
    ],
    "Patterns": {
      "bearish_engulfing": false,
      "black_solders": false,
      "builish_engulfing": false,
      "doji": false,
      "dragonfly_doji": false,
      "gravestone_doji": false,
      "hammer": false,
      "white_solders": false
    }
  }
}