{
  "symbol": "BTCUSDT",
  "time": "2026-05-02 02:25:03.541202",
  "label_return": 0.0018790607495123867,
  "indicators": {
    "SMA": 78403.77999999998,
    "EMA": 78395.50656777903,
    "Trend15": "Flat",
    "RSI": 33.073101490420825,
    "MACD": {
      "MACDLine": -16.442348077747738,
      "SignalLine": -8.486497514960421,
      "Histogram": -7.955850562787317
    },
    "ATR": 19.678571428571427,
    "ATRPercent": 0.0251203726313221,
    "ADX": 29.060035356950358,
    "Volume": "Volume Down",
    "Supports": [
      78690.6,
      78692.2,
      78650,
      78771.9,
      78764.3,
      78621.5,
      78615.7,
      78626.2,
      78657.4,
      78576.4,
      78577.4,
      78576.8,
      78699.4,
      78666.4,
      78626.9,
      78685.4,
      78676.1,
      78729.2,
      78720.9,
      78665.9,
      78489.1,
      78424.9,
      78395.2,
      78387.4,
      78381.4,
      78386.4,
      78404.5,
      78378.6,
      78416.7,
      78398.6,
      78398.5,
      78408.7,
      78427,
      78406.6,
      78397.9,
      78359.3,
      78396.2,
      78393.1,
      78330.3
    ],
    "Resistances": [
      78741.8,
      78730.5,
      78717.4,
      78730.4,
      78696.4,
      78746.7,
      78800,
      78843.3,
      78811.1,
      78794.8,
      78690.3,
      78634.1,
      78673.5,
      78725,
      78690.5,
      78614.3,
      78691.3,
      78744.1,
      78748.1,
      78741.8,
      78772.7,
      78740.8,
      78779.8,
      78872.4,
      78843.3,
      79182.5,
      78503.2,
      78447.3,
      78480,
      78479.6,
      78413.9,
      78401.2,
      78410.5,
      78398,
      78413.5,
      78456,
      78488.9,
      78428,
      78470,
      78432.1,
      78431.5,
      78470.9,
      78416.1,
      78395.5,
      78410,
      78417
    ],
    "Patterns": {
      "bearish_engulfing": false,
      "black_solders": false,
      "builish_engulfing": false,
      "doji": true,
      "dragonfly_doji": true,
      "gravestone_doji": false,
      "hammer": false,
      "white_solders": false
    }
  }
}