{
  "symbol": "BTCUSDT",
  "time": "2023-12-16 16:25:45.090758",
  "label_return": 0.0005747139809063981,
  "indicators": {
    "SMA": 43024.656,
    "EMA": 42901.35560874436,
    "Trend15": "Up",
    "RSI": 44.45015416238438,
    "MACD": {
      "MACDLine": 34.30112356921745,
      "SignalLine": 53.462603427231244,
      "Histogram": -19.16147985801379
    },
    "ATR": 139.49285714285725,
    "ATRPercent": 0.323957493538766,
    "ADX": 1.4900093333021291,
    "Volume": "Volume Down",
    "Supports": [
      42326.4,
      42330.4,
      42554,
      42501.6,
      42408,
      42400.1,
      42351.6,
      42353.5,
      42271.9,
      42157.3,
      42230.7,
      42208.4,
      42248.2,
      42130.4,
      41890.8,
      41872,
      41916.9,
      41785.3,
      41825.1,
      41680,
      41850.5,
      41921.6,
      41870.8,
      41902,
      41793.2,
      41527.9,
      41581.8,
      41716,
      41799.3,
      42078.8,
      41945,
      41644.6,
      41255.5,
      41200.4,
      40888,
      40965.1,
      40810,
      41053.9,
      41021,
      41039.7,
      40816.7,
      40566,
      40972.5,
      40981.5,
      40922.1,
      41286.7,
      41165,
      41321.7,
      41360,
      41656.5,
      41584.1,
      42462.8,
      42471.8,
      42608.2,
      42646.2,
      43066.8,
      43025.8,
      42878.5,
      42843.7,
      42919.5,
      42948.8,
      43020.8,
      43043.1,
      42984.6,
      42972.1,
      42985
    ],
    "Resistances": [
      42486,
      42472.5,
      42685.2,
      42783.3,
      42613.2,
      42517,
      42554.9,
      42440,
      42404,
      42356.2,
      42374.4,
      42328.6,
      42305.8,
      42279.5,
      42171.8,
      42037.1,
      42088.3,
      42079,
      42010,
      42082.8,
      42025.8,
      41998,
      42052.2,
      42010.3,
      42044.5,
      42008.4,
      41984.5,
      41825,
      41896.3,
      42479.2,
      42293.2,
      42211.6,
      42222.7,
      41860.5,
      41449.9,
      41149,
      41130,
      41228.8,
      41220,
      41272.9,
      41318.6,
      41348.3,
      41284.5,
      41175.5,
      41245.3,
      41158.6,
      41517.5,
      41776.9,
      41449.8,
      41679.8,
      41768.4,
      41872.5,
      42677.3,
      42810.6,
      42758.9,
      42984.1,
      42870,
      43548,
      43166.6,
      43028.5,
      43219.1,
      43150.1,
      43313.4
    ],
    "Patterns": {
      "bearish_engulfing": false,
      "black_solders": false,
      "builish_engulfing": false,
      "doji": false,
      "dragonfly_doji": false,
      "gravestone_doji": false,
      "hammer": false,
      "white_solders": false
    }
  }
}