{
  "symbol": "BTCUSDT",
  "time": "2026-02-09 16:25:45.090758",
  "label_return": -0.0031078476095177405,
  "indicators": {
    "SMA": 67397.51599999999,
    "EMA": 67442.24051515675,
    "Trend15": "Down",
    "RSI": 82.65639445300482,
    "MACD": {
      "MACDLine": 223.72324936317455,
      "SignalLine": 140.71426574544037,
      "Histogram": 83.00898361773417
    },
    "ATR": 268.25714285714224,
    "ATRPercent": 0.39447549443358393,
    "ADX": 35.62113254754225,
    "Volume": "Volume Down",
    "Supports": [
      68207.2,
      68779.9,
      69051.9,
      69821.4,
      70050,
      70464,
      69780.7,
      70220.3,
      69715.8,
      69149.3,
      69153.6,
      68603.7,
      68823.1,
      68680.6,
      68907.6,
      68783.9,
      68365,
      68286.2,
      68831.9,
      67869,
      68900.1,
      69224.7,
      68565,
      68583.6,
      68315,
      68517.3,
      68471.3,
      68875,
      67956.1,
      67321,
      66611.3,
      66501.5,
      66746,
      66605.3,
      66306.8,
      66768.4,
      65705,
      66009,
      65840,
      66108.4,
      67266.7,
      67138.4,
      67354.3,
      66755.3,
      67371.5,
      67277,
      66626.7,
      66894.3,
      66858.1,
      67381.8
    ],
    "Resistances": [
      69747.5,
      69843.6,
      69690.3,
      70397.8,
      70976.9,
      70989,
      70510.2,
      71119.9,
      70841.1,
      70714.3,
      70591.5,
      70508.8,
      69828.6,
      69874.9,
      69465.2,
      69173.2,
      69385.2,
      69221,
      69050,
      68791.5,
      68819.9,
      69552.7,
      69481.6,
      69805.8,
      69982.2,
      69911.7,
      69268.3,
      68978.7,
      68760,
      68830,
      69216,
      69265.8,
      69135,
      67780,
      67137.9,
      67241.7,
      67084,
      66973.7,
      66862.6,
      67080,
      67394.9,
      67190.3,
      67667.5,
      68812.6,
      66811,
      67238.6,
      66894.7,
      67837.7,
      67723.3,
      68329,
      67687.2,
      67678.2,
      68019.9,
      67739.8,
      67668.4,
      67327.4,
      67308,
      67320,
      67708.9,
      68271.4
    ],
    "Patterns": {
      "bearish_engulfing": false,
      "black_solders": true,
      "builish_engulfing": false,
      "doji": false,
      "dragonfly_doji": false,
      "gravestone_doji": false,
      "hammer": false,
      "white_solders": false
    }
  }
}