{
  "symbol": "BTCUSDT",
  "time": "2025-12-29 16:25:45.090758",
  "label_return": -0.00016257944222748514,
  "indicators": {
    "SMA": 87756.82,
    "EMA": 87792.35194479531,
    "Trend15": "Down",
    "RSI": 82.20744128039863,
    "MACD": {
      "MACDLine": 60.605311433100724,
      "SignalLine": 38.84527725457641,
      "Histogram": 21.760034178524315
    },
    "ATR": 77.3214285714317,
    "ATRPercent": 0.08790161904632335,
    "ADX": 36.9554857149145,
    "Volume": "Volume Down",
    "Supports": [
      87100,
      87166.4,
      87538.5,
      87378.2,
      87306,
      87266,
      87234.4,
      87039.8,
      87029.3,
      87132,
      87066,
      87068.7,
      87045,
      86924.2,
      86779.2,
      87090.9,
      87322.1,
      87600,
      87873.4,
      87857.4,
      87717.1,
      87901.9,
      87870.1,
      87783.3,
      87836.1,
      88531,
      88463.8,
      88040.2,
      87909.3,
      87823.4,
      88244,
      88126.6,
      88500,
      88480.5,
      88340.1,
      88272.7,
      88375,
      88350.2,
      88621,
      88767.5,
      88693.7,
      88704,
      87863.5,
      87730.5,
      87342,
      87441.9,
      87641.3,
      87362.3,
      87177.8,
      87722.2,
      87615.2,
      87573.4,
      87574,
      87676.2,
      87790,
      87850,
      87515,
      87605.9,
      87590,
      87555.8,
      87645.9,
      87740.7,
      87828.9
    ],
    "Resistances": [
      88148.8,
      87888,
      87732.2,
      87962.2,
      87645.7,
      87567.3,
      87337.9,
      87328,
      87365.3,
      87325.9,
      87263.2,
      87322.7,
      87287,
      87450,
      87420,
      87326.6,
      87564.5,
      88200,
      87950,
      88080.2,
      88153.7,
      88080.1,
      88118,
      88376.2,
      89038.2,
      89127,
      89373,
      88867.2,
      88460.1,
      88396.1,
      88442.4,
      88553.2,
      88767.5,
      88719.8,
      88849.3,
      88521,
      88496.3,
      88534.7,
      88713.2,
      88904.3,
      88918.2,
      89059.8,
      88868.4,
      89194.3,
      88109.5,
      88012.8,
      87700.5,
      87938.5,
      87512.5,
      87834.9,
      87842,
      87770.8,
      88022.1,
      88054,
      87984.3,
      87711.9,
      87641.4,
      87639.6,
      87631.7,
      87769.3,
      87756.3,
      87911.9,
      87842.3,
      87949.7
    ],
    "Patterns": {
      "bearish_engulfing": false,
      "black_solders": false,
      "builish_engulfing": false,
      "doji": false,
      "dragonfly_doji": false,
      "gravestone_doji": false,
      "hammer": false,
      "white_solders": false
    }
  }
}