{
  "symbol": "BTCUSDT",
  "time": "2024-06-28 16:25:45.090758",
  "label_return": 0.002730646364557958,
  "indicators": {
    "SMA": 63134.04000000001,
    "EMA": 62882.79919528287,
    "Trend15": "Up",
    "RSI": 31.17556665386114,
    "MACD": {
      "MACDLine": -125.58301788295648,
      "SignalLine": -104.32440287999958,
      "Histogram": -21.2586150029569
    },
    "ATR": 135.3428571428558,
    "ATRPercent": 0.21601596247149954,
    "ADX": 34.543720611409235,
    "Volume": "Volume Down",
    "Supports": [
      61200,
      60695.4,
      60568.1,
      60670.8,
      60616,
      60170,
      60011.5,
      60113.7,
      60260,
      60265.5,
      60518.5,
      60721.5,
      60640.8,
      60655.1,
      60672.5,
      60882.5,
      60870,
      60886,
      60897.6,
      61037.5,
      60962.5,
      60932.7,
      60918.5,
      60880.1,
      60900.9,
      60953.7,
      60886.8,
      60961.3,
      60906,
      60762.3,
      60871.5,
      60887.4,
      60703.6,
      60750,
      60673,
      60724.1,
      61368.7,
      61404.2,
      61463.4,
      61479.9,
      61464.9,
      61485,
      61280.5,
      61489,
      61540.7,
      61621,
      61777.2,
      61796.9,
      62804.6,
      62556.3,
      63422,
      63258.1,
      63303.2,
      63165,
      63246.2,
      63294,
      63201.3,
      62787,
      62750,
      62734.3,
      62560.3
    ],
    "Resistances": [
      61148.8,
      61045.8,
      60846.8,
      60826.5,
      60450,
      60333.3,
      60360,
      60400,
      60416.9,
      60778.7,
      60959.8,
      60950,
      60764.5,
      60771.8,
      60753.2,
      60825,
      61115.2,
      60977.6,
      60976.3,
      61012.4,
      61198.9,
      61156,
      61020,
      61111,
      61040,
      61049.7,
      61059,
      61074,
      61030,
      61037.2,
      61040.8,
      61007.6,
      60919.5,
      60842.9,
      60925.3,
      60865.2,
      60776.8,
      61776.5,
      61696.6,
      61588,
      61606.3,
      61639.1,
      61622.3,
      61715.2,
      61835,
      61653.8,
      61737,
      61828.5,
      62077.7,
      62077,
      62392.3,
      62939,
      63041.3,
      62934.3,
      63790,
      63492.8,
      63439.8,
      63419.9,
      63470,
      63322,
      62962.2,
      62951.7,
      62918.5
    ],
    "Patterns": {
      "bearish_engulfing": false,
      "black_solders": false,
      "builish_engulfing": false,
      "doji": true,
      "dragonfly_doji": false,
      "gravestone_doji": true,
      "hammer": false,
      "white_solders": false
    }
  }
}